odoo/addons/l10n_es_aeat_mod190/README.rst
odoo/addons/l10n_es_aeat_mod190/__init__.py
odoo/addons/l10n_es_aeat_mod190/__manifest__.py
odoo/addons/l10n_es_aeat_mod190/data/l10n.es.aeat.map.tax.csv
odoo/addons/l10n_es_aeat_mod190/data/l10n.es.aeat.map.tax.line.csv
odoo/addons/l10n_es_aeat_mod190/data/l10n.es.aeat.map.tax.line.tax.csv
odoo/addons/l10n_es_aeat_mod190/data/perception_key_data.xml
odoo/addons/l10n_es_aeat_mod190/data/perception_subkey_data.xml
odoo/addons/l10n_es_aeat_mod190/data/2017/aeat.model.export.config.csv
odoo/addons/l10n_es_aeat_mod190/data/2017/aeat.model.export.config.line.csv
odoo/addons/l10n_es_aeat_mod190/data/2025/aeat.model.export.config.csv
odoo/addons/l10n_es_aeat_mod190/data/2025/aeat.model.export.config.line.csv
odoo/addons/l10n_es_aeat_mod190/docs/DR190_2017.pdf
odoo/addons/l10n_es_aeat_mod190/docs/DR190_2024.pdf
odoo/addons/l10n_es_aeat_mod190/i18n/ca.po
odoo/addons/l10n_es_aeat_mod190/i18n/ca_ES.po
odoo/addons/l10n_es_aeat_mod190/i18n/es.po
odoo/addons/l10n_es_aeat_mod190/i18n/l10n_es_aeat_mod190.pot
odoo/addons/l10n_es_aeat_mod190/migrations/18.0.1.0.0/pre-migration.py
odoo/addons/l10n_es_aeat_mod190/models/__init__.py
odoo/addons/l10n_es_aeat_mod190/models/account_fiscal_position.py
odoo/addons/l10n_es_aeat_mod190/models/account_move.py
odoo/addons/l10n_es_aeat_mod190/models/account_move_line.py
odoo/addons/l10n_es_aeat_mod190/models/l10n_es_aeat_mod190_report.py
odoo/addons/l10n_es_aeat_mod190/models/l10n_es_aeat_perception.py
odoo/addons/l10n_es_aeat_mod190/models/res_partner.py
odoo/addons/l10n_es_aeat_mod190/readme/CONFIGURE.md
odoo/addons/l10n_es_aeat_mod190/readme/CONTRIBUTORS.md
odoo/addons/l10n_es_aeat_mod190/readme/DESCRIPTION.md
odoo/addons/l10n_es_aeat_mod190/readme/ROADMAP.md
odoo/addons/l10n_es_aeat_mod190/readme/USAGE.md
odoo/addons/l10n_es_aeat_mod190/security/ir.model.access.csv
odoo/addons/l10n_es_aeat_mod190/security/l10n_es_aeat_mod190_security.xml
odoo/addons/l10n_es_aeat_mod190/static/description/icon.png
odoo_addon_l10n_es_aeat_mod190-18.0.1.2.0.1.dist-info/METADATA
odoo_addon_l10n_es_aeat_mod190-18.0.1.2.0.1.dist-info/WHEEL
odoo_addon_l10n_es_aeat_mod190-18.0.1.2.0.1.dist-info/top_level.txt
odoo_addon_l10n_es_aeat_mod190-18.0.1.2.0.1.dist-info/RECORD
